aiida_test_cache/__init__.py
aiida_test_cache/_config.py
aiida_test_cache/py.typed
aiida_test_cache/archive_cache/__init__.py
aiida_test_cache/archive_cache/_fixtures.py
aiida_test_cache/archive_cache/_utils.py
aiida_test_cache/mock_code/__init__.py
aiida_test_cache/mock_code/_cli.py
aiida_test_cache/mock_code/_env_keys.py
aiida_test_cache/mock_code/_fixtures.py
aiida_test_cache/mock_code/_hasher.py
aiida_test_cache-0.0.1.dist-info/entry_points.txt
aiida_test_cache-0.0.1.dist-info/LICENSE.txt
aiida_test_cache-0.0.1.dist-info/WHEEL
aiida_test_cache-0.0.1.dist-info/METADATA
aiida_test_cache-0.0.1.dist-info/RECORD
